zdppy_code/__init__.py
zdppy_code/code.py
zdppy_code/msg.py
zdppy_code/response.py
zdppy_code-0.1.0.dist-info/LICENSE
zdppy_code-0.1.0.dist-info/WHEEL
zdppy_code-0.1.0.dist-info/METADATA
zdppy_code-0.1.0.dist-info/RECORD
